scorecard/__init__.py
scorecard/api.py
scorecard/exceptions.py
scorecard/objects.py
college_scorecard-1.4.dist-info/LICENSE
college_scorecard-1.4.dist-info/METADATA
college_scorecard-1.4.dist-info/WHEEL
college_scorecard-1.4.dist-info/top_level.txt
college_scorecard-1.4.dist-info/RECORD
