Metadata-Version: 2.1
Name: college-scorecard
Version: 1.4
Summary: A python library for collegescorecard.ed.gov
Home-page: https://github.com/ahoodatheguy/scorecard
Author: Ahadu Kebede
Author-email: ahadukebede@gmail.com
License-File: LICENSE
